{
  "count": 248,
  "days": [
    {
      "count": 6,
      "date": "2021-01-01",
      "members": [
        "70",
        "72",
        "67",
        "49",
        "41",
        "57"
      ]
    },
    {
      "count": 5,
      "date": "2021-01-02",
      "members": [
        "56",
        "45",
        "79",
        "69",
        "76"
      ]
    },
    {
      "count": 2,
      "date": "2021-01-03",
      "members": [
        "27",
        "77"
      ]
    },
    {
      "count": 2,
      "date": "2021-01-04",
      "members": [
        "51",
        "80"
      ]
    },
    {
      "count": 1,
      "date": "2021-01-05",
      "members": [
        "79"
      ]
    },
    {
      "count": 2,
      "date": "2021-01-06",
      "members": [
        "53",
        "45"
      ]
    },
    {
      "count": 4,
      "date": "2021-01-07",
      "members": [
        "78",
        "57",
        "70",
        "73"
      ]
    },
    {
      "count": 8,
      "date": "2021-01-08",
      "members": [
        "42",
        "77",
        "34",
        "53",
        "52",
        "60",
        "76",
        "58"
      ]
    },
    {
      "count": 2,
      "date": "2021-01-09",
      "members": [
        "61",
        "56"
      ]
    },
    {
      "count": 2,
      "date": "2021-01-10",
      "members": [
        "29",
        "45"
      ]
    },
    {
      "count": 4,
      "date": "2021-01-11",
      "members": [
        "58",
        "62",
        "43",
        "55"
      ]
    },
    {
      "count": 6,
      "date": "2021-01-12",
      "members": [
        "80",
        "78",
        "71",
        "65",
        "77",
        "69"
      ]
    },
    {
      "count": 2,
      "date": "2021-01-13",
      "members": [
        "56",
        "03"
      ]
    },
    {
      "count": 2,
      "date": "2021-01-14",
      "members": [
        "67",
        "73"
      ]
    },
    {
      "count": 6,
      "date": "2021-01-15",
      "members": [
        "56",
        "77",
        "47",
        "79",
        "43",
        "57"
      ]
    },
    {
      "count": 2,
      "date": "2021-01-16",
      "members": [
        "76",
        "69"
      ]
    },
    {
      "count": 1,
      "date": "2021-01-17",
      "members": [
        "14"
      ]
    },
    {
      "count": 2,
      "date": "2021-01-18",
      "members": [
        "68",
        "78"
      ]
    },
    {
      "count": 8,
      "date": "2021-01-19",
      "members": [
        "42",
        "56",
        "73",
        "78",
        "76",
        "37",
        "27",
        "43"
      ]
    },
    {
      "count": 3,
      "date": "2021-01-20",
      "members": [
        "64",
        "78",
        "70"
      ]
    },
    {
      "count": 8,
      "date": "2021-01-21",
      "members": [
        "77",
        "77",
        "79",
        "57",
        "58",
        "73",
        "77",
        "77"
      ]
    },
    {
      "count": 4,
      "date": "2021-01-22",
      "members": [
        "66",
        "80",
        "70",
        "79"
      ]
    },
    {
      "count": 3,
      "date": "2021-01-23",
      "members": [
        "66",
        "77",
        "65"
      ]
    },
    {
      "count": 4,
      "date": "2021-01-24",
      "members": [
        "69",
        "68",
        "70",
        "76"
      ]
    },
    {
      "count": 5,
      "date": "2021-01-25",
      "members": [
        "56",
        "52",
        "42",
        "78",
        "61"
      ]
    },
    {
      "count": 2,
      "date": "2021-01-26",
      "members": [
        "80",
        "68"
      ]
    },
    {
      "count": 5,
      "date": "2021-01-27",
      "members": [
        "77",
        "73",
        "57",
        "01",
        "60"
      ]
    },
    {
      "count": 1,
      "date": "2021-01-28",
      "members": [
        "73"
      ]
    },
    {
      "count": 8,
      "date": "2021-01-29",
      "members": [
        "56",
        "69",
        "79",
        "76",
        "73",
        "71",
        "72",
        "27"
      ]
    },
    {
      "count": 1,
      "date": "2021-01-30",
      "members": [
        "57"
      ]
    },
    {
      "count": 4,
      "date": "2021-01-31",
      "members": [
        "78",
        "74",
        "77",
        "34"
      ]
    },
    {
      "count": 2,
      "date": "2021-02-01",
      "members": [
        "76",
        "47"
      ]
    },
    {
      "count": 7,
      "date": "2021-02-02",
      "members": [
        "56",
        "78",
        "27",
        "67",
        "69",
        "60",
        "52"
      ]
    },
    {
      "count": 2,
      "date": "2021-02-03",
      "members": [
        "80",
        "79"
      ]
    },
    {
      "count": 3,
      "date": "2021-02-04",
      "members": [
        "77",
        "47",
        "57"
      ]
    },
    {
      "count": 4,
      "date": "2021-02-05",
      "members": [
        "42",
        "68",
        "78",
        "76"
      ]
    },
    {
      "count": 3,
      "date": "2021-02-06",
      "members": [
        "73",
        "74",
        "29"
      ]
    },
    {
      "count": 1,
      "date": "2021-02-07",
      "members": [
        "37"
      ]
    },
    {
      "count": 8,
      "date": "2021-02-08",
      "members": [
        "19",
        "47",
        "77",
        "56",
        "66",
        "45",
        "70",
        "47"
      ]
    },
    {
      "count": 0,
      "date": "2021-02-09",
      "members": []
    },
    {
      "count": 7,
      "date": "2021-02-10",
      "members": [
        "67",
        "56",
        "79",
        "57",
        "58",
        "64",
        "55"
      ]
    },
    {
      "count": 5,
      "date": "2021-02-11",
      "members": [
        "68",
        "73",
        "43",
        "65",
        "76"
      ]
    },
    {
      "count": 4,
      "date": "2021-02-12",
      "members": [
        "69",
        "30",
        "47",
        "53"
      ]
    },
    {
      "count": 4,
      "date": "2021-02-13",
      "members": [
        "80",
        "74",
        "34",
        "78"
      ]
    },
    {
      "count": 5,
      "date": "2021-02-14",
      "members": [
        "77",
        "55",
        "73",
        "58",
        "71"
      ]
    },
    {
      "count": 0,
      "date": "2021-02-15",
      "members": []
    },
    {
      "count": 5,
      "date": "2021-02-16",
      "members": [
        "47",
        "51",
        "80",
        "77",
        "78"
      ]
    },
    {
      "count": 2,
      "date": "2021-02-17",
      "members": [
        "56",
        "65"
      ]
    },
    {
      "count": 5,
      "date": "2021-02-18",
      "members": [
        "43",
        "79",
        "57",
        "76",
        "73"
      ]
    },
    {
      "count": 0,
      "date": "2021-02-19",
      "members": []
    },
    {
      "count": 1,
      "date": "2021-02-20",
      "members": [
        "60"
      ]
    },
    {
      "count": 2,
      "date": "2021-02-21",
      "members": [
        "30",
        "69"
      ]
    },
    {
      "count": 2,
      "date": "2021-02-22",
      "members": [
        "27",
        "43"
      ]
    },
    {
      "count": 4,
      "date": "2021-02-23",
      "members": [
        "56",
        "68",
        "57",
        "76"
      ]
    },
    {
      "count": 1,
      "date": "2021-02-24",
      "members": [
        "03"
      ]
    },
    {
      "count": 2,
      "date": "2021-02-25",
      "members": [
        "73",
        "58"
      ]
    },
    {
      "count": 5,
      "date": "2021-02-26",
      "members": [
        "77",
        "54",
        "79",
        "45",
        "47"
      ]
    },
    {
      "count": 1,
      "date": "2021-02-27",
      "members": [
        "42"
      ]
    },
    {
      "count": 5,
      "date": "2021-02-28",
      "members": [
        "56",
        "57",
        "55",
        "67",
        "77"
      ]
    },
    {
      "count": 3,
      "date": "2021-03-01",
      "members": [
        "74",
        "52",
        "70"
      ]
    },
    {
      "count": 4,
      "date": "2021-03-02",
      "members": [
        "72",
        "68",
        "43",
        "69"
      ]
    },
    {
      "count": 4,
      "date": "2021-03-03",
      "members": [
        "66",
        "80",
        "01",
        "70"
      ]
    },
    {
      "count": 6,
      "date": "2021-03-04",
      "members": [
        "56",
        "71",
        "29",
        "57",
        "76",
        "73"
      ]
    },
    {
      "count": 1,
      "date": "2021-03-05",
      "members": [
        "59"
      ]
    },
    {
      "count": 2,
      "date": "2021-03-06",
      "members": [
        "79",
        "43"
      ]
    },
    {
      "count": 3,
      "date": "2021-03-07",
      "members": [
        "77",
        "68",
        "73"
      ]
    },
    {
      "count": 5,
      "date": "2021-03-08",
      "members": [
        "78",
        "67",
        "80",
        "56",
        "52"
      ]
    },
    {
      "count": 3,
      "date": "2021-03-09",
      "members": [
        "64",
        "55",
        "53"
      ]
    },
    {
      "count": 2,
      "date": "2021-03-10",
      "members": [
        "77",
        "57"
      ]
    },
    {
      "count": 4,
      "date": "2021-03-11",
      "members": [
        "42",
        "55",
        "43",
        "77"
      ]
    },
    {
      "count": 3,
      "date": "2021-03-12",
      "members": [
        "73",
        "69",
        "76"
      ]
    },
    {
      "count": 3,
      "date": "2021-03-13",
      "members": [
        "79",
        "65",
        "58"
      ]
    },
    {
      "count": 0,
      "date": "2021-03-14",
      "members": []
    }
  ],
  "months": [
    {
      "name": "Jan",
      "weekIndex": 0
    },
    {
      "name": "Feb",
      "weekIndex": 5
    },
    {
      "name": "Mar",
      "weekIndex": 9
    }
  ],
  "offset": 5,
  "weekCount": 12,
  "year": 2021
}