{
  "count": 46,
  "days": [
    {
      "count": 5,
      "date": "2025-01-01",
      "members": [
        "85",
        "72",
        "84",
        "83",
        "89"
      ]
    },
    {
      "count": 1,
      "date": "2025-01-02",
      "members": [
        "86"
      ]
    },
    {
      "count": 2,
      "date": "2025-01-03",
      "members": [
        "65",
        "79"
      ]
    },
    {
      "count": 3,
      "date": "2025-01-04",
      "members": [
        "92",
        "90",
        "83"
      ]
    },
    {
      "count": 2,
      "date": "2025-01-05",
      "members": [
        "78",
        "62"
      ]
    },
    {
      "count": 1,
      "date": "2025-01-06",
      "members": [
        "67"
      ]
    },
    {
      "count": 2,
      "date": "2025-01-07",
      "members": [
        "90",
        "77"
      ]
    },
    {
      "count": 0,
      "date": "2025-01-08",
      "members": []
    },
    {
      "count": 0,
      "date": "2025-01-09",
      "members": []
    },
    {
      "count": 0,
      "date": "2025-01-10",
      "members": []
    },
    {
      "count": 1,
      "date": "2025-01-11",
      "members": [
        "74"
      ]
    },
    {
      "count": 3,
      "date": "2025-01-12",
      "members": [
        "83",
        "71",
        "86"
      ]
    },
    {
      "count": 0,
      "date": "2025-01-13",
      "members": []
    },
    {
      "count": 1,
      "date": "2025-01-14",
      "members": [
        "52"
      ]
    },
    {
      "count": 2,
      "date": "2025-01-15",
      "members": [
        "83",
        "69"
      ]
    },
    {
      "count": 1,
      "date": "2025-01-16",
      "members": [
        "83"
      ]
    },
    {
      "count": 0,
      "date": "2025-01-17",
      "members": []
    },
    {
      "count": 2,
      "date": "2025-01-18",
      "members": [
        "82",
        "65"
      ]
    },
    {
      "count": 2,
      "date": "2025-01-19",
      "members": [
        "76",
        "90"
      ]
    },
    {
      "count": 5,
      "date": "2025-01-20",
      "members": [
        "77",
        "79",
        "88",
        "83",
        "87"
      ]
    },
    {
      "count": 1,
      "date": "2025-01-21",
      "members": [
        "67"
      ]
    },
    {
      "count": 0,
      "date": "2025-01-22",
      "members": []
    },
    {
      "count": 0,
      "date": "2025-01-23",
      "members": []
    },
    {
      "count": 0,
      "date": "2025-01-24",
      "members": []
    },
    {
      "count": 2,
      "date": "2025-01-25",
      "members": [
        "82",
        "83"
      ]
    },
    {
      "count": 3,
      "date": "2025-01-26",
      "members": [
        "82",
        "64",
        "89"
      ]
    },
    {
      "count": 7,
      "date": "2025-01-27",
      "members": [
        "82",
        "86",
        "79",
        "91",
        "83",
        "57",
        "71"
      ]
    }
  ],
  "months": [
    {
      "name": "Jan",
      "weekIndex": 0
    }
  ],
  "offset": 3,
  "weekCount": 5,
  "year": 2025
}